radifox/utils/__init__.py
radifox/utils/_static_version.py
radifox/utils/_version.py
radifox/utils/degrade/__init__.py
radifox/utils/degrade/degrade.py
radifox/utils/degrade/degrade_fourier.py
radifox/utils/degrade/degrade_slice_selection.py
radifox/utils/degrade/tests/__init__.py
radifox/utils/degrade/tests/test_degrade.py
radifox/utils/resize/__init__.py
radifox/utils/resize/abstract.py
radifox/utils/resize/affine.py
radifox/utils/resize/pytorch.py
radifox/utils/resize/scipy.py
radifox/utils/resize/tests/compare_interp.py
radifox/utils/resize/tests/test_resize_affine.py
radifox/utils/resize/tests/test_resize_pytorch.py
radifox/utils/resize/tests/test_resize_scipy.py
radifox_utils-1.0.6.dist-info/LICENSE
radifox_utils-1.0.6.dist-info/METADATA
radifox_utils-1.0.6.dist-info/WHEEL
radifox_utils-1.0.6.dist-info/entry_points.txt
radifox_utils-1.0.6.dist-info/top_level.txt
radifox_utils-1.0.6.dist-info/RECORD
