Metadata-Version: 2.1
Name: radifox-utils
Version: 1.0.6
Summary: Medical image utilities provided with RADIFOX
Author-email: JH-MIPC <jhmipc@jh.edu>
License: Apache-2.0
Project-URL: Homepage, https://github.com/jh-mipc/radifox-utils
Classifier: Programming Language :: Python :: 3
Classifier: License :: OSI Approved :: Apache Software License
Classifier: Operating System :: OS Independent
Requires-Python: >=3.7
License-File: LICENSE
Requires-Dist: nibabel
Requires-Dist: numpy
Requires-Dist: scipy
Requires-Dist: sigpy-lite
Requires-Dist: transforms3d
